cmdbroker/__init__.py
cmdbroker/__main__.py
cmdbroker/cli.py
cmdbroker/client.py
cmdbroker/message.py
cmdbroker/server.py
cmdbroker-0.0.4.dist-info/LICENSE
cmdbroker-0.0.4.dist-info/METADATA
cmdbroker-0.0.4.dist-info/WHEEL
cmdbroker-0.0.4.dist-info/entry_points.txt
cmdbroker-0.0.4.dist-info/RECORD
