Metadata-Version: 2.1
Name: cmdbroker
Version: 0.0.4
Summary: Broker commands to a server
License: MIT
Author: Brad Pitcher
Author-email: bradpitcher@gmail.com
Requires-Python: >=3.10
Classifier: License :: OSI Approved :: MIT License
Classifier: Programming Language :: Python :: 3
Classifier: Programming Language :: Python :: 3.10
Classifier: Programming Language :: Python :: 3.11
Classifier: Programming Language :: Python :: 3.12
Requires-Dist: cryptography (>=42.0.8,<43.0.0)
